setup.py
basic_probability_distributions/Binomialdistribution.py
basic_probability_distributions/Gaussiandistribution.py
basic_probability_distributions/Generaldistribution.py
basic_probability_distributions/__init__.py
basic_probability_distributions.egg-info/PKG-INFO
basic_probability_distributions.egg-info/SOURCES.txt
basic_probability_distributions.egg-info/dependency_links.txt
basic_probability_distributions.egg-info/not-zip-safe
basic_probability_distributions.egg-info/top_level.txt